pyneoinstance/__init__.py
pyneoinstance/database/__init__.py
pyneoinstance/database/context.py
pyneoinstance/database/neo4jdbms.py
pyneoinstance/fileload/__init__.py
pyneoinstance/fileload/context.py
pyneoinstance/fileload/helpers.py
pyneoinstance/fileload/loadyaml.py
pyneoinstance/util/__init__.py
pyneoinstance/util/functions.py
pyneoinstance-3.0.0.dist-info/licenses/LICENSE
test/__init__.py
test/age_data.csv
test/context.py
test/cypher_queries.yaml
test/load_files.yaml
test/movies.csv
test/people.csv
test/roles.csv
test/test.py
test/test_fileload.py
test/test_neo4jdb.py
test/test_util_functions.py
pyneoinstance-3.0.0.dist-info/METADATA
pyneoinstance-3.0.0.dist-info/WHEEL
pyneoinstance-3.0.0.dist-info/top_level.txt
pyneoinstance-3.0.0.dist-info/RECORD
