Metadata-Version: 2.4
Name: pyneoinstance
Version: 3.0.0
Summary: Handle Neo4j read and write transactions and provide methos for performing graph EDA
Author-email: "Jose A. Alvarado-Guzman" <jose.alvarado-guzman@neo4j.com>
License: GNU GENERAL PUBLIC LICENSE
Keywords: neo4j,graph,cypher
Classifier: License :: OSI Approved :: GNU General Public License (GPL)
Classifier: Programming Language :: Python :: 3
Classifier: Development Status :: 4 - Beta
Requires-Python: >=3.8
License-File: LICENSE
Requires-Dist: neo4j>=5.0.0
Requires-Dist: pandas
Requires-Dist: PyYAML
Requires-Dist: pyvis
Dynamic: license-file
